dify_client/__init__.py
dify_client/async_dify_client.py
dify_client/async_request.py
dify_client/auth.py
dify_client/config.py
dify_client/exception.py
dify_client/logger.py
dify_client/model.py
dify_client/paginator.py
dify_client/rate_limit.py
dify_client/request.py
dify_client/retry.py
dify_client/stream.py
dify_client/timeout.py
dify_client/trace.py
dify_client/util.py
dify_client/version.py
dify_client/chat/__init__.py
dify_client/chat/async_client.py
dify_client/datasets/__init__.py
dify_client/datasets/async_client.py
dify_client/files/__init__.py
dify_client/files/async_client.py
dify_client/templates/__init__.py
dify_client/workflows/__init__.py
dify_client/workflows/async_client.py
difypy-0.1.2.dist-info/LICENSE
difypy-0.1.2.dist-info/METADATA
difypy-0.1.2.dist-info/WHEEL
difypy-0.1.2.dist-info/top_level.txt
difypy-0.1.2.dist-info/RECORD
