Metadata-Version: 2.1
Name: difypy
Version: 0.1.2
Summary: Python SDK for Dify API
Home-page: https://github.com/likunpm/difypy
Author: likun.pm
Author-email: likun2440@gmail.com
License: UNKNOWN
Platform: UNKNOWN
Classifier: Programming Language :: Python :: 3
Classifier: License :: OSI Approved :: MIT License
Classifier: Operating System :: OS Independent
Requires-Python: >=3.7
License-File: LICENSE
Requires-Dist: requests (>=2.25.1)
Requires-Dist: aiohttp (>=3.8.0)
